compropago/__init__.py
compropago/exceptions.py
compropago/tests.py
compropago_python-0.3.dist-info/DESCRIPTION.rst
compropago_python-0.3.dist-info/METADATA
compropago_python-0.3.dist-info/RECORD
compropago_python-0.3.dist-info/WHEEL
compropago_python-0.3.dist-info/metadata.json
compropago_python-0.3.dist-info/top_level.txt
