Metadata-Version: 2.0
Name: compropago-python
Version: 0.3
Summary: Python library for ComproPago
Home-page: http://github.io/tzicatl/compropago-python
Author: Noe Nieto
Author-email: nnieto@noenieto.com
License: MIT
Keywords: ecommerce e-commerce payment development mexico
Platform: UNKNOWN
Classifier: Development Status :: 4 - Beta
Classifier: Environment :: No Input/Output (Daemon)
Classifier: Environment :: Web Environment
Classifier: Intended Audience :: Developers
Classifier: License :: OSI Approved :: MIT License
Classifier: Natural Language :: Spanish
Classifier: Operating System :: OS Independent
Classifier: Programming Language :: Python :: 2.7
Requires-Dist: requests
Provides-Extra: dev
Requires-Dist: nose (>=1.0); extra == 'dev'
Requires-Dist: responses; extra == 'dev'
